cmask2polygons.py
cmask2polygons-1.1.3.dist-info/LICENSE
cmask2polygons-1.1.3.dist-info/METADATA
cmask2polygons-1.1.3.dist-info/WHEEL
cmask2polygons-1.1.3.dist-info/top_level.txt
cmask2polygons-1.1.3.dist-info/RECORD
