Metadata-Version: 2.1
Name: cmask2polygons
Version: 1.1.3
Summary: Convert Color label mask to Polygons per class
Home-page: https://github.com/DevBruce/cmask2polygons
Author: devbruce
Author-email: bruce93k@gmail.com
License: MIT
Keywords: mask,polygon
Platform: UNKNOWN
Requires-Python: >=3.6.5
Requires-Dist: numpy (>=1.19.0)
Requires-Dist: opencv-python (>=4.3.0.36)
